{
  "scope": "state_house",
  "contest_type": "state_house",
  "year": 2016,
  "meta": {
    "source": "tn_precinct_csv_district_aggregation",
    "match_coverage_pct": 100.0,
    "direct_precinct_row_pct": 0.0,
    "county_fallback_row_pct": 0.0,
    "dropped_row_pct": 0.0,
    "direct_precinct_vote_pct": 0.0,
    "county_fallback_vote_pct": 0.0,
    "dropped_vote_pct": 0.0,
    "districts": 99
  },
  "general": {
    "results": {
      "1": {
        "dem_votes": 0,
        "rep_votes": 18730,
        "other_votes": 0,
        "total_votes": 18730,
        "dem_candidate": "",
        "rep_candidate": "John Crawford",
        "margin": 18730,
        "margin_pct": 100.0,
        "winner": "REP"
      },
      "2": {
        "dem_votes": 4940,
        "rep_votes": 20334,
        "other_votes": 0,
        "total_votes": 25274,
        "dem_candidate": "J. S. Moore",
        "rep_candidate": "Bud Hulsey",
        "margin": 15394,
        "margin_pct": 60.9084,
        "winner": "REP"
      },
      "3": {
        "dem_votes": 0,
        "rep_votes": 19316,
        "other_votes": 3129,
        "total_votes": 22445,
        "dem_candidate": "",
        "rep_candidate": "Timothy Hill",
        "margin": 19316,
        "margin_pct": 86.0593,
        "winner": "REP"
      },
      "4": {
        "dem_votes": 0,
        "rep_votes": 19061,
        "other_votes": 0,
        "total_votes": 19061,
        "dem_candidate": "",
        "rep_candidate": "John B. Holsclaw Jr.",
        "margin": 19061,
        "margin_pct": 100.0,
        "winner": "REP"
      },
      "5": {
        "dem_votes": 0,
        "rep_votes": 17516,
        "other_votes": 0,
        "total_votes": 17516,
        "dem_candidate": "",
        "rep_candidate": "David B. Hawk",
        "margin": 17516,
        "margin_pct": 100.0,
        "winner": "REP"
      },
      "6": {
        "dem_votes": 6807,
        "rep_votes": 18213,
        "other_votes": 0,
        "total_votes": 25020,
        "dem_candidate": "John Baker",
        "rep_candidate": "Micah Van Huss",
        "margin": 11406,
        "margin_pct": 45.5875,
        "winner": "REP"
      },
      "7": {
        "dem_votes": 6840,
        "rep_votes": 14385,
        "other_votes": 0,
        "total_votes": 21225,
        "dem_candidate": "Nancy Fischman",
        "rep_candidate": "Matthew Hill",
        "margin": 7545,
        "margin_pct": 35.5477,
        "winner": "REP"
      },
      "8": {
        "dem_votes": 0,
        "rep_votes": 21723,
        "other_votes": 0,
        "total_votes": 21723,
        "dem_candidate": "",
        "rep_candidate": "Art Swann",
        "margin": 21723,
        "margin_pct": 100.0,
        "winner": "REP"
      },
      "9": {
        "dem_votes": 0,
        "rep_votes": 15536,
        "other_votes": 4516,
        "total_votes": 20052,
        "dem_candidate": "",
        "rep_candidate": "Gary W Hicks Jr",
        "margin": 15536,
        "margin_pct": 77.4786,
        "winner": "REP"
      },
      "10": {
        "dem_votes": 0,
        "rep_votes": 15374,
        "other_votes": 0,
        "total_votes": 15374,
        "dem_candidate": "",
        "rep_candidate": "Tilman Goins",
        "margin": 15374,
        "margin_pct": 100.0,
        "winner": "REP"
      },
      "11": {
        "dem_votes": 4374,
        "rep_votes": 15318,
        "other_votes": 0,
        "total_votes": 19692,
        "dem_candidate": "Marjorie Ramsey",
        "rep_candidate": "Jeremy Faison",
        "margin": 10944,
        "margin_pct": 55.5759,
        "winner": "REP"
      },
      "12": {
        "dem_votes": 0,
        "rep_votes": 21152,
        "other_votes": 339,
        "total_votes": 21491,
        "dem_candidate": "",
        "rep_candidate": "Dale Carr",
        "margin": 21152,
        "margin_pct": 98.4226,
        "winner": "REP"
      },
      "13": {
        "dem_votes": 11011,
        "rep_votes": 11162,
        "other_votes": 0,
        "total_votes": 22173,
        "dem_candidate": "Gloria Johnson",
        "rep_candidate": "Eddie Smith",
        "margin": 151,
        "margin_pct": 0.681,
        "winner": "REP"
      },
      "14": {
        "dem_votes": 9235,
        "rep_votes": 24849,
        "other_votes": 0,
        "total_votes": 34084,
        "dem_candidate": "Scott Hacker",
        "rep_candidate": "Jason Zachary",
        "margin": 15614,
        "margin_pct": 45.8104,
        "winner": "REP"
      },
      "15": {
        "dem_votes": 9242,
        "rep_votes": 0,
        "other_votes": 5485,
        "total_votes": 14727,
        "dem_candidate": "Rick Staples",
        "rep_candidate": "",
        "margin": -9242,
        "margin_pct": -62.7555,
        "winner": "DEM"
      },
      "16": {
        "dem_votes": 0,
        "rep_votes": 21815,
        "other_votes": 0,
        "total_votes": 21815,
        "dem_candidate": "",
        "rep_candidate": "Bill Dunn",
        "margin": 21815,
        "margin_pct": 100.0,
        "winner": "REP"
      },
      "17": {
        "dem_votes": 0,
        "rep_votes": 18185,
        "other_votes": 0,
        "total_votes": 18185,
        "dem_candidate": "",
        "rep_candidate": "Andrew Ellis Farmer",
        "margin": 18185,
        "margin_pct": 100.0,
        "winner": "REP"
      },
      "18": {
        "dem_votes": 10742,
        "rep_votes": 15572,
        "other_votes": 0,
        "total_votes": 26314,
        "dem_candidate": "Brandi Price",
        "rep_candidate": "Martin Daniel",
        "margin": 4830,
        "margin_pct": 18.3552,
        "winner": "REP"
      },
      "19": {
        "dem_votes": 0,
        "rep_votes": 20364,
        "other_votes": 0,
        "total_votes": 20364,
        "dem_candidate": "",
        "rep_candidate": "Harry Brooks",
        "margin": 20364,
        "margin_pct": 100.0,
        "winner": "REP"
      },
      "20": {
        "dem_votes": 0,
        "rep_votes": 19106,
        "other_votes": 4669,
        "total_votes": 23775,
        "dem_candidate": "",
        "rep_candidate": "Bob Ramsey",
        "margin": 19106,
        "margin_pct": 80.3617,
        "winner": "REP"
      },
      "21": {
        "dem_votes": 5447,
        "rep_votes": 21087,
        "other_votes": 916,
        "total_votes": 27450,
        "dem_candidate": "Pamela \"Pam\" Weston",
        "rep_candidate": "Jimmy Matlock",
        "margin": 15640,
        "margin_pct": 56.9763,
        "winner": "REP"
      },
      "22": {
        "dem_votes": 4486,
        "rep_votes": 20064,
        "other_votes": 0,
        "total_votes": 24550,
        "dem_candidate": "Anna Miller Grabowski",
        "rep_candidate": "Dan Howell",
        "margin": 15578,
        "margin_pct": 63.4542,
        "winner": "REP"
      },
      "23": {
        "dem_votes": 0,
        "rep_votes": 19998,
        "other_votes": 3337,
        "total_votes": 23335,
        "dem_candidate": "",
        "rep_candidate": "John Forgety",
        "margin": 19998,
        "margin_pct": 85.6996,
        "winner": "REP"
      },
      "24": {
        "dem_votes": 0,
        "rep_votes": 18465,
        "other_votes": 0,
        "total_votes": 18465,
        "dem_candidate": "",
        "rep_candidate": "Kevin D Brooks",
        "margin": 18465,
        "margin_pct": 100.0,
        "winner": "REP"
      },
      "25": {
        "dem_votes": 6077,
        "rep_votes": 22335,
        "other_votes": 0,
        "total_votes": 28412,
        "dem_candidate": "Judy Barnett",
        "rep_candidate": "Cameron Sexton",
        "margin": 16258,
        "margin_pct": 57.2223,
        "winner": "REP"
      },
      "26": {
        "dem_votes": 0,
        "rep_votes": 24935,
        "other_votes": 0,
        "total_votes": 24935,
        "dem_candidate": "",
        "rep_candidate": "Gerald McCormick",
        "margin": 24935,
        "margin_pct": 100.0,
        "winner": "REP"
      },
      "27": {
        "dem_votes": 8142,
        "rep_votes": 20995,
        "other_votes": 0,
        "total_votes": 29137,
        "dem_candidate": "Steve Gordon",
        "rep_candidate": "Patsy Hazlewood",
        "margin": 12853,
        "margin_pct": 44.1123,
        "winner": "REP"
      },
      "28": {
        "dem_votes": 18490,
        "rep_votes": 0,
        "other_votes": 39,
        "total_votes": 18529,
        "dem_candidate": "JoAnne Favors",
        "rep_candidate": "",
        "margin": -18490,
        "margin_pct": -99.7895,
        "winner": "DEM"
      },
      "29": {
        "dem_votes": 0,
        "rep_votes": 23169,
        "other_votes": 0,
        "total_votes": 23169,
        "dem_candidate": "",
        "rep_candidate": "Mike Carter",
        "margin": 23169,
        "margin_pct": 100.0,
        "winner": "REP"
      },
      "30": {
        "dem_votes": 8622,
        "rep_votes": 17044,
        "other_votes": 916,
        "total_votes": 26582,
        "dem_candidate": "Katie R. Cowley",
        "rep_candidate": "Marc Gravitt",
        "margin": 8422,
        "margin_pct": 31.6831,
        "winner": "REP"
      },
      "31": {
        "dem_votes": 0,
        "rep_votes": 19816,
        "other_votes": 0,
        "total_votes": 19816,
        "dem_candidate": "",
        "rep_candidate": "Ron Travis",
        "margin": 19816,
        "margin_pct": 100.0,
        "winner": "REP"
      },
      "32": {
        "dem_votes": 3409,
        "rep_votes": 15627,
        "other_votes": 5836,
        "total_votes": 24872,
        "dem_candidate": "Corey B. Stafford",
        "rep_candidate": "Kent D. Calfee",
        "margin": 12218,
        "margin_pct": 49.1235,
        "winner": "REP"
      },
      "33": {
        "dem_votes": 8057,
        "rep_votes": 15743,
        "other_votes": 0,
        "total_votes": 23800,
        "dem_candidate": "Michael S McKamey",
        "rep_candidate": "John D Ragan",
        "margin": 7686,
        "margin_pct": 32.2941,
        "winner": "REP"
      },
      "34": {
        "dem_votes": 9939,
        "rep_votes": 19962,
        "other_votes": 0,
        "total_votes": 29901,
        "dem_candidate": "Laura Bohling",
        "rep_candidate": "Tim Rudd",
        "margin": 10023,
        "margin_pct": 33.5206,
        "winner": "REP"
      },
      "35": {
        "dem_votes": 0,
        "rep_votes": 15949,
        "other_votes": 0,
        "total_votes": 15949,
        "dem_candidate": "",
        "rep_candidate": "Jerry Sexton",
        "margin": 15949,
        "margin_pct": 100.0,
        "winner": "REP"
      },
      "36": {
        "dem_votes": 5297,
        "rep_votes": 13944,
        "other_votes": 0,
        "total_votes": 19241,
        "dem_candidate": "Bob Fannon",
        "rep_candidate": "Dennis H. Powers",
        "margin": 8647,
        "margin_pct": 44.9405,
        "winner": "REP"
      },
      "37": {
        "dem_votes": 9640,
        "rep_votes": 14744,
        "other_votes": 0,
        "total_votes": 24384,
        "dem_candidate": "Becky Goff",
        "rep_candidate": "Dawn White",
        "margin": 5104,
        "margin_pct": 20.9318,
        "winner": "REP"
      },
      "38": {
        "dem_votes": 3841,
        "rep_votes": 16988,
        "other_votes": 0,
        "total_votes": 20829,
        "dem_candidate": "F. Mike Campbell",
        "rep_candidate": "Kelly T Keisling",
        "margin": 13147,
        "margin_pct": 63.1187,
        "winner": "REP"
      },
      "39": {
        "dem_votes": 7522,
        "rep_votes": 15920,
        "other_votes": 0,
        "total_votes": 23442,
        "dem_candidate": "Nancy Silvertooth",
        "rep_candidate": "David Alexander",
        "margin": 8398,
        "margin_pct": 35.8246,
        "winner": "REP"
      },
      "40": {
        "dem_votes": 7450,
        "rep_votes": 20364,
        "other_votes": 0,
        "total_votes": 27814,
        "dem_candidate": "Gayla Colvert Hendrix",
        "rep_candidate": "Terri Lynn Weaver",
        "margin": 12914,
        "margin_pct": 46.4299,
        "winner": "REP"
      },
      "41": {
        "dem_votes": 12238,
        "rep_votes": 10021,
        "other_votes": 0,
        "total_votes": 22259,
        "dem_candidate": "John Mark Windle",
        "rep_candidate": "Ed Butler",
        "margin": -2217,
        "margin_pct": -9.96,
        "winner": "DEM"
      },
      "42": {
        "dem_votes": 5986,
        "rep_votes": 17486,
        "other_votes": 0,
        "total_votes": 23472,
        "dem_candidate": "Amos Scott Powers",
        "rep_candidate": "Ryan D Williams",
        "margin": 11500,
        "margin_pct": 48.9945,
        "winner": "REP"
      },
      "43": {
        "dem_votes": 10213,
        "rep_votes": 11692,
        "other_votes": 0,
        "total_votes": 21905,
        "dem_candidate": "Kevin Dunlap",
        "rep_candidate": "Paul Sherrell",
        "margin": 1479,
        "margin_pct": 6.7519,
        "winner": "REP"
      },
      "44": {
        "dem_votes": 5642,
        "rep_votes": 18009,
        "other_votes": 0,
        "total_votes": 23651,
        "dem_candidate": "Lloyd Dunn",
        "rep_candidate": "William Lamberth",
        "margin": 12367,
        "margin_pct": 52.2895,
        "winner": "REP"
      },
      "45": {
        "dem_votes": 0,
        "rep_votes": 23234,
        "other_votes": 337,
        "total_votes": 23571,
        "dem_candidate": "",
        "rep_candidate": "Courtney L. Rogers",
        "margin": 23234,
        "margin_pct": 98.5703,
        "winner": "REP"
      },
      "46": {
        "dem_votes": 6589,
        "rep_votes": 19785,
        "other_votes": 0,
        "total_votes": 26374,
        "dem_candidate": "Amelia Morrison Hipps",
        "rep_candidate": "Mark Pody",
        "margin": 13196,
        "margin_pct": 50.0341,
        "winner": "REP"
      },
      "47": {
        "dem_votes": 0,
        "rep_votes": 19874,
        "other_votes": 0,
        "total_votes": 19874,
        "dem_candidate": "",
        "rep_candidate": "Judd Matheny",
        "margin": 19874,
        "margin_pct": 100.0,
        "winner": "REP"
      },
      "48": {
        "dem_votes": 8726,
        "rep_votes": 16381,
        "other_votes": 0,
        "total_votes": 25107,
        "dem_candidate": "Justin T. Miller",
        "rep_candidate": "Bryan Terry",
        "margin": 7655,
        "margin_pct": 30.4895,
        "winner": "REP"
      },
      "49": {
        "dem_votes": 8604,
        "rep_votes": 13531,
        "other_votes": 0,
        "total_votes": 22135,
        "dem_candidate": "Brandon Thomas",
        "rep_candidate": "Mike Sparks",
        "margin": 4927,
        "margin_pct": 22.2589,
        "winner": "REP"
      },
      "50": {
        "dem_votes": 15188,
        "rep_votes": 13861,
        "other_votes": 0,
        "total_votes": 29049,
        "dem_candidate": "Bo Mitchell",
        "rep_candidate": "Nathan Massey",
        "margin": -1327,
        "margin_pct": -4.5681,
        "winner": "DEM"
      },
      "51": {
        "dem_votes": 19893,
        "rep_votes": 0,
        "other_votes": 0,
        "total_votes": 19893,
        "dem_candidate": "Bill Beck",
        "rep_candidate": "",
        "margin": -19893,
        "margin_pct": -100.0,
        "winner": "DEM"
      },
      "52": {
        "dem_votes": 14545,
        "rep_votes": 0,
        "other_votes": 0,
        "total_votes": 14545,
        "dem_candidate": "Michael Stewart",
        "rep_candidate": "",
        "margin": -14545,
        "margin_pct": -100.0,
        "winner": "DEM"
      },
      "53": {
        "dem_votes": 12457,
        "rep_votes": 9208,
        "other_votes": 3,
        "total_votes": 21668,
        "dem_candidate": "Jason Powell",
        "rep_candidate": "Davette Blalock",
        "margin": -3249,
        "margin_pct": -14.9945,
        "winner": "DEM"
      },
      "54": {
        "dem_votes": 19782,
        "rep_votes": 0,
        "other_votes": 3251,
        "total_votes": 23033,
        "dem_candidate": "Brenda Gilmore",
        "rep_candidate": "",
        "margin": -19782,
        "margin_pct": -85.8855,
        "winner": "DEM"
      },
      "55": {
        "dem_votes": 19254,
        "rep_votes": 0,
        "other_votes": 0,
        "total_votes": 19254,
        "dem_candidate": "John Ray Clemmons",
        "rep_candidate": "",
        "margin": -19254,
        "margin_pct": -100.0,
        "winner": "DEM"
      },
      "56": {
        "dem_votes": 15224,
        "rep_votes": 21069,
        "other_votes": 0,
        "total_votes": 36293,
        "dem_candidate": "Chris Moth",
        "rep_candidate": "Beth Harwell",
        "margin": 5845,
        "margin_pct": 16.105,
        "winner": "REP"
      },
      "57": {
        "dem_votes": 10870,
        "rep_votes": 24444,
        "other_votes": 0,
        "total_votes": 35314,
        "dem_candidate": "Trisha Farmer",
        "rep_candidate": "Susan M Lynn",
        "margin": 13574,
        "margin_pct": 38.438,
        "winner": "REP"
      },
      "58": {
        "dem_votes": 15901,
        "rep_votes": 0,
        "other_votes": 0,
        "total_votes": 15901,
        "dem_candidate": "Harold M. Love, Jr.",
        "rep_candidate": "",
        "margin": -15901,
        "margin_pct": -100.0,
        "winner": "DEM"
      },
      "59": {
        "dem_votes": 12874,
        "rep_votes": 0,
        "other_votes": 0,
        "total_votes": 12874,
        "dem_candidate": "Sherry Jones",
        "rep_candidate": "",
        "margin": -12874,
        "margin_pct": -100.0,
        "winner": "DEM"
      },
      "60": {
        "dem_votes": 15103,
        "rep_votes": 11799,
        "other_votes": 0,
        "total_votes": 26902,
        "dem_candidate": "Darren Jernigan",
        "rep_candidate": "Steve Glover",
        "margin": -3304,
        "margin_pct": -12.2816,
        "winner": "DEM"
      },
      "61": {
        "dem_votes": 0,
        "rep_votes": 29366,
        "other_votes": 0,
        "total_votes": 29366,
        "dem_candidate": "",
        "rep_candidate": "Charles M. Sargent Jr",
        "margin": 29366,
        "margin_pct": 100.0,
        "winner": "REP"
      },
      "62": {
        "dem_votes": 4824,
        "rep_votes": 15954,
        "other_votes": 0,
        "total_votes": 20778,
        "dem_candidate": "Sharon Kay Edwards",
        "rep_candidate": "Pat Marsh",
        "margin": 11130,
        "margin_pct": 53.5663,
        "winner": "REP"
      },
      "63": {
        "dem_votes": 11125,
        "rep_votes": 28390,
        "other_votes": 0,
        "total_votes": 39515,
        "dem_candidate": "Courtenay Rogers",
        "rep_candidate": "Glen Casada",
        "margin": 17265,
        "margin_pct": 43.6923,
        "winner": "REP"
      },
      "64": {
        "dem_votes": 0,
        "rep_votes": 19984,
        "other_votes": 7516,
        "total_votes": 27500,
        "dem_candidate": "",
        "rep_candidate": "Sheila Butt",
        "margin": 19984,
        "margin_pct": 72.6691,
        "winner": "REP"
      },
      "65": {
        "dem_votes": 8947,
        "rep_votes": 21649,
        "other_votes": 0,
        "total_votes": 30596,
        "dem_candidate": "Holly McCall",
        "rep_candidate": "Sam Whitson",
        "margin": 12702,
        "margin_pct": 41.5152,
        "winner": "REP"
      },
      "66": {
        "dem_votes": 6589,
        "rep_votes": 18432,
        "other_votes": 0,
        "total_votes": 25021,
        "dem_candidate": "Larry Proffitt",
        "rep_candidate": "Sabi (Doc) Kumar",
        "margin": 11843,
        "margin_pct": 47.3322,
        "winner": "REP"
      },
      "67": {
        "dem_votes": 10564,
        "rep_votes": 0,
        "other_votes": 6562,
        "total_votes": 17126,
        "dem_candidate": "Joe Pitts",
        "rep_candidate": "",
        "margin": -10564,
        "margin_pct": -61.684,
        "winner": "DEM"
      },
      "68": {
        "dem_votes": 0,
        "rep_votes": 22757,
        "other_votes": 0,
        "total_votes": 22757,
        "dem_candidate": "",
        "rep_candidate": "Curtis Johnson",
        "margin": 22757,
        "margin_pct": 100.0,
        "winner": "REP"
      },
      "69": {
        "dem_votes": 7391,
        "rep_votes": 14144,
        "other_votes": 0,
        "total_votes": 21535,
        "dem_candidate": "Dustin Evans",
        "rep_candidate": "Michael G. Curcio",
        "margin": 6753,
        "margin_pct": 31.3583,
        "winner": "REP"
      },
      "70": {
        "dem_votes": 5645,
        "rep_votes": 15365,
        "other_votes": 2000,
        "total_votes": 23010,
        "dem_candidate": "Calvin Moore",
        "rep_candidate": "Barry Doss",
        "margin": 9720,
        "margin_pct": 42.2425,
        "winner": "REP"
      },
      "71": {
        "dem_votes": 0,
        "rep_votes": 18413,
        "other_votes": 0,
        "total_votes": 18413,
        "dem_candidate": "",
        "rep_candidate": "David \"Coach\" Byrd",
        "margin": 18413,
        "margin_pct": 100.0,
        "winner": "REP"
      },
      "72": {
        "dem_votes": 0,
        "rep_votes": 20009,
        "other_votes": 0,
        "total_votes": 20009,
        "dem_candidate": "",
        "rep_candidate": "Steve McDaniel",
        "margin": 20009,
        "margin_pct": 100.0,
        "winner": "REP"
      },
      "73": {
        "dem_votes": 0,
        "rep_votes": 22252,
        "other_votes": 0,
        "total_votes": 22252,
        "dem_candidate": "",
        "rep_candidate": "Jimmy Eldridge",
        "margin": 22252,
        "margin_pct": 100.0,
        "winner": "REP"
      },
      "74": {
        "dem_votes": 8021,
        "rep_votes": 11260,
        "other_votes": 0,
        "total_votes": 19281,
        "dem_candidate": "Andy Porch",
        "rep_candidate": "Jay D. Reedy",
        "margin": 3239,
        "margin_pct": 16.7989,
        "winner": "REP"
      },
      "75": {
        "dem_votes": 5771,
        "rep_votes": 14816,
        "other_votes": 1917,
        "total_votes": 22504,
        "dem_candidate": "Daniel Powell",
        "rep_candidate": "Tim Wirgau",
        "margin": 9045,
        "margin_pct": 40.1929,
        "winner": "REP"
      },
      "76": {
        "dem_votes": 4327,
        "rep_votes": 13038,
        "other_votes": 3215,
        "total_votes": 20580,
        "dem_candidate": "Angela Callis",
        "rep_candidate": "Andy Holt",
        "margin": 8711,
        "margin_pct": 42.3275,
        "winner": "REP"
      },
      "77": {
        "dem_votes": 0,
        "rep_votes": 16326,
        "other_votes": 3809,
        "total_votes": 20135,
        "dem_candidate": "",
        "rep_candidate": "Bill Sanderson",
        "margin": 16326,
        "margin_pct": 81.0827,
        "winner": "REP"
      },
      "78": {
        "dem_votes": 6539,
        "rep_votes": 18679,
        "other_votes": 0,
        "total_votes": 25218,
        "dem_candidate": "Travis S. Staten",
        "rep_candidate": "Mary Littleton",
        "margin": 12140,
        "margin_pct": 48.1402,
        "winner": "REP"
      },
      "79": {
        "dem_votes": 0,
        "rep_votes": 17131,
        "other_votes": 0,
        "total_votes": 17131,
        "dem_candidate": "",
        "rep_candidate": "Curtis Halford",
        "margin": 17131,
        "margin_pct": 100.0,
        "winner": "REP"
      },
      "80": {
        "dem_votes": 14847,
        "rep_votes": 0,
        "other_votes": 0,
        "total_votes": 14847,
        "dem_candidate": "Johnny W. Shaw",
        "rep_candidate": "",
        "margin": -14847,
        "margin_pct": -100.0,
        "winner": "DEM"
      },
      "81": {
        "dem_votes": 4842,
        "rep_votes": 15535,
        "other_votes": 0,
        "total_votes": 20377,
        "dem_candidate": "Deborah K. Reed",
        "rep_candidate": "Debra Moody",
        "margin": 10693,
        "margin_pct": 52.4758,
        "winner": "REP"
      },
      "82": {
        "dem_votes": 10443,
        "rep_votes": 8220,
        "other_votes": 0,
        "total_votes": 18663,
        "dem_candidate": "Craig Fitzhugh",
        "rep_candidate": "Andy Cole",
        "margin": -2223,
        "margin_pct": -11.9113,
        "winner": "DEM"
      },
      "83": {
        "dem_votes": 9506,
        "rep_votes": 16900,
        "other_votes": 0,
        "total_votes": 26406,
        "dem_candidate": "Lawrence A. Pivnick",
        "rep_candidate": "Mark White",
        "margin": 7394,
        "margin_pct": 28.0012,
        "winner": "REP"
      },
      "84": {
        "dem_votes": 17577,
        "rep_votes": 0,
        "other_votes": 0,
        "total_votes": 17577,
        "dem_candidate": "Joe Towns, Jr.",
        "rep_candidate": "",
        "margin": -17577,
        "margin_pct": -100.0,
        "winner": "DEM"
      },
      "85": {
        "dem_votes": 20732,
        "rep_votes": 0,
        "other_votes": 0,
        "total_votes": 20732,
        "dem_candidate": "Johnnie R. Turner",
        "rep_candidate": "",
        "margin": -20732,
        "margin_pct": -100.0,
        "winner": "DEM"
      },
      "86": {
        "dem_votes": 14945,
        "rep_votes": 5442,
        "other_votes": 0,
        "total_votes": 20387,
        "dem_candidate": "Barbara Cooper",
        "rep_candidate": "George T. Edwards, III",
        "margin": -9503,
        "margin_pct": -46.613,
        "winner": "DEM"
      },
      "87": {
        "dem_votes": 16601,
        "rep_votes": 0,
        "other_votes": 0,
        "total_votes": 16601,
        "dem_candidate": "Karen Camper",
        "rep_candidate": "",
        "margin": -16601,
        "margin_pct": -100.0,
        "winner": "DEM"
      },
      "88": {
        "dem_votes": 14918,
        "rep_votes": 0,
        "other_votes": 2834,
        "total_votes": 17752,
        "dem_candidate": "Larry J. Miller",
        "rep_candidate": "",
        "margin": -14918,
        "margin_pct": -84.0356,
        "winner": "DEM"
      },
      "89": {
        "dem_votes": 8305,
        "rep_votes": 19735,
        "other_votes": 0,
        "total_votes": 28040,
        "dem_candidate": "Heather C. Hensley",
        "rep_candidate": "Roger Kane",
        "margin": 11430,
        "margin_pct": 40.7632,
        "winner": "REP"
      },
      "90": {
        "dem_votes": 16362,
        "rep_votes": 0,
        "other_votes": 0,
        "total_votes": 16362,
        "dem_candidate": "John J. Deberry, Jr.",
        "rep_candidate": "",
        "margin": -16362,
        "margin_pct": -100.0,
        "winner": "DEM"
      },
      "91": {
        "dem_votes": 14580,
        "rep_votes": 3125,
        "other_votes": 0,
        "total_votes": 17705,
        "dem_candidate": "Raumesh Akbari",
        "rep_candidate": "Samuel A. Arthur Watkins",
        "margin": -11455,
        "margin_pct": -64.6992,
        "winner": "DEM"
      },
      "92": {
        "dem_votes": 5693,
        "rep_votes": 16475,
        "other_votes": 0,
        "total_votes": 22168,
        "dem_candidate": "Tamra King",
        "rep_candidate": "Thomas R. Tillis",
        "margin": 10782,
        "margin_pct": 48.6377,
        "winner": "REP"
      },
      "93": {
        "dem_votes": 13832,
        "rep_votes": 0,
        "other_votes": 2666,
        "total_votes": 16498,
        "dem_candidate": "G. A. Hardaway",
        "rep_candidate": "",
        "margin": -13832,
        "margin_pct": -83.8405,
        "winner": "DEM"
      },
      "94": {
        "dem_votes": 6088,
        "rep_votes": 20006,
        "other_votes": 0,
        "total_votes": 26094,
        "dem_candidate": "Daniel M. Harris",
        "rep_candidate": "Ron M. Gant",
        "margin": 13918,
        "margin_pct": 53.3379,
        "winner": "REP"
      },
      "95": {
        "dem_votes": 0,
        "rep_votes": 26586,
        "other_votes": 0,
        "total_votes": 26586,
        "dem_candidate": "",
        "rep_candidate": "Mark Lovell",
        "margin": 26586,
        "margin_pct": 100.0,
        "winner": "REP"
      },
      "96": {
        "dem_votes": 14150,
        "rep_votes": 13785,
        "other_votes": 0,
        "total_votes": 27935,
        "dem_candidate": "Dwayne Thompson",
        "rep_candidate": "Stephen McManus",
        "margin": -365,
        "margin_pct": -1.3066,
        "winner": "DEM"
      },
      "97": {
        "dem_votes": 0,
        "rep_votes": 17163,
        "other_votes": 0,
        "total_votes": 17163,
        "dem_candidate": "",
        "rep_candidate": "Jim Coley",
        "margin": 17163,
        "margin_pct": 100.0,
        "winner": "REP"
      },
      "98": {
        "dem_votes": 13406,
        "rep_votes": 0,
        "other_votes": 0,
        "total_votes": 13406,
        "dem_candidate": "Antonio Parkinson",
        "rep_candidate": "",
        "margin": -13406,
        "margin_pct": -100.0,
        "winner": "DEM"
      },
      "99": {
        "dem_votes": 0,
        "rep_votes": 22874,
        "other_votes": 0,
        "total_votes": 22874,
        "dem_candidate": "",
        "rep_candidate": "Ron Lollar",
        "margin": 22874,
        "margin_pct": 100.0,
        "winner": "REP"
      }
    }
  }
}