{
  "scope": "state_house",
  "contest_type": "us_senate",
  "year": 2014,
  "meta": {
    "source": "tn_precinct_csv_district_aggregation",
    "match_coverage_pct": 100.0,
    "districts": 79
  },
  "general": {
    "results": {
      "1": {
        "dem_votes": 1845,
        "rep_votes": 7341,
        "other_votes": 667,
        "total_votes": 9853,
        "dem_candidate": "Gordon Ball",
        "rep_candidate": "Lamar Alexander",
        "margin": 5496,
        "margin_pct": 55.78,
        "winner": "REP"
      },
      "2": {
        "dem_votes": 2682,
        "rep_votes": 10228,
        "other_votes": 1003,
        "total_votes": 13913,
        "dem_candidate": "Gordon Ball",
        "rep_candidate": "Lamar Alexander",
        "margin": 7546,
        "margin_pct": 54.237,
        "winner": "REP"
      },
      "3": {
        "dem_votes": 2714,
        "rep_votes": 10668,
        "other_votes": 1120,
        "total_votes": 14502,
        "dem_candidate": "Gordon Ball",
        "rep_candidate": "Lamar Alexander",
        "margin": 7954,
        "margin_pct": 54.8476,
        "winner": "REP"
      },
      "4": {
        "dem_votes": 2171,
        "rep_votes": 8614,
        "other_votes": 879,
        "total_votes": 11664,
        "dem_candidate": "Gordon Ball",
        "rep_candidate": "Lamar Alexander",
        "margin": 6443,
        "margin_pct": 55.2383,
        "winner": "REP"
      },
      "5": {
        "dem_votes": 20,
        "rep_votes": 61,
        "other_votes": 9,
        "total_votes": 90,
        "dem_candidate": "Gordon Ball",
        "rep_candidate": "Lamar Alexander",
        "margin": 41,
        "margin_pct": 45.5556,
        "winner": "REP"
      },
      "6": {
        "dem_votes": 337,
        "rep_votes": 964,
        "other_votes": 91,
        "total_votes": 1392,
        "dem_candidate": "Gordon Ball",
        "rep_candidate": "Lamar Alexander",
        "margin": 627,
        "margin_pct": 45.0431,
        "winner": "REP"
      },
      "7": {
        "dem_votes": 643,
        "rep_votes": 2001,
        "other_votes": 203,
        "total_votes": 2847,
        "dem_candidate": "Gordon Ball",
        "rep_candidate": "Lamar Alexander",
        "margin": 1358,
        "margin_pct": 47.6993,
        "winner": "REP"
      },
      "8": {
        "dem_votes": 2728,
        "rep_votes": 7947,
        "other_votes": 827,
        "total_votes": 11502,
        "dem_candidate": "Gordon Ball",
        "rep_candidate": "Lamar Alexander",
        "margin": 5219,
        "margin_pct": 45.3747,
        "winner": "REP"
      },
      "9": {
        "dem_votes": 852,
        "rep_votes": 3012,
        "other_votes": 289,
        "total_votes": 4153,
        "dem_candidate": "Gordon Ball",
        "rep_candidate": "Lamar Alexander",
        "margin": 2160,
        "margin_pct": 52.0106,
        "winner": "REP"
      },
      "10": {
        "dem_votes": 2342,
        "rep_votes": 7680,
        "other_votes": 618,
        "total_votes": 10640,
        "dem_candidate": "Gordon Ball",
        "rep_candidate": "Lamar Alexander",
        "margin": 5338,
        "margin_pct": 50.1692,
        "winner": "REP"
      },
      "11": {
        "dem_votes": 3136,
        "rep_votes": 6481,
        "other_votes": 608,
        "total_votes": 10225,
        "dem_candidate": "Gordon Ball",
        "rep_candidate": "Lamar Alexander",
        "margin": 3345,
        "margin_pct": 32.7139,
        "winner": "REP"
      },
      "12": {
        "dem_votes": 2213,
        "rep_votes": 8731,
        "other_votes": 771,
        "total_votes": 11715,
        "dem_candidate": "Gordon Ball",
        "rep_candidate": "Lamar Alexander",
        "margin": 6518,
        "margin_pct": 55.6381,
        "winner": "REP"
      },
      "13": {
        "dem_votes": 5000,
        "rep_votes": 11644,
        "other_votes": 1099,
        "total_votes": 17743,
        "dem_candidate": "Gordon Ball",
        "rep_candidate": "Lamar Alexander",
        "margin": 6644,
        "margin_pct": 37.4458,
        "winner": "REP"
      },
      "14": {
        "dem_votes": 2128,
        "rep_votes": 3797,
        "other_votes": 461,
        "total_votes": 6386,
        "dem_candidate": "Gordon Ball",
        "rep_candidate": "Lamar Alexander",
        "margin": 1669,
        "margin_pct": 26.1353,
        "winner": "REP"
      },
      "15": {
        "dem_votes": 2721,
        "rep_votes": 5883,
        "other_votes": 539,
        "total_votes": 9143,
        "dem_candidate": "Gordon Ball",
        "rep_candidate": "Lamar Alexander",
        "margin": 3162,
        "margin_pct": 34.5838,
        "winner": "REP"
      },
      "16": {
        "dem_votes": 2580,
        "rep_votes": 6854,
        "other_votes": 530,
        "total_votes": 9964,
        "dem_candidate": "Gordon Ball",
        "rep_candidate": "Lamar Alexander",
        "margin": 4274,
        "margin_pct": 42.8944,
        "winner": "REP"
      },
      "17": {
        "dem_votes": 2578,
        "rep_votes": 8482,
        "other_votes": 781,
        "total_votes": 11841,
        "dem_candidate": "Gordon Ball",
        "rep_candidate": "Lamar Alexander",
        "margin": 5904,
        "margin_pct": 49.8607,
        "winner": "REP"
      },
      "18": {
        "dem_votes": 1757,
        "rep_votes": 4305,
        "other_votes": 421,
        "total_votes": 6483,
        "dem_candidate": "Gordon Ball",
        "rep_candidate": "Lamar Alexander",
        "margin": 2548,
        "margin_pct": 39.3028,
        "winner": "REP"
      },
      "19": {
        "dem_votes": 3840,
        "rep_votes": 4153,
        "other_votes": 703,
        "total_votes": 8696,
        "dem_candidate": "Gordon Ball",
        "rep_candidate": "Lamar Alexander",
        "margin": 313,
        "margin_pct": 3.5994,
        "winner": "REP"
      },
      "20": {
        "dem_votes": 2561,
        "rep_votes": 7012,
        "other_votes": 709,
        "total_votes": 10282,
        "dem_candidate": "Gordon Ball",
        "rep_candidate": "Lamar Alexander",
        "margin": 4451,
        "margin_pct": 43.2892,
        "winner": "REP"
      },
      "21": {
        "dem_votes": 2000,
        "rep_votes": 7151,
        "other_votes": 535,
        "total_votes": 9686,
        "dem_candidate": "Gordon Ball",
        "rep_candidate": "Lamar Alexander",
        "margin": 5151,
        "margin_pct": 53.1798,
        "winner": "REP"
      },
      "22": {
        "dem_votes": 1646,
        "rep_votes": 7323,
        "other_votes": 528,
        "total_votes": 9497,
        "dem_candidate": "Gordon Ball",
        "rep_candidate": "Lamar Alexander",
        "margin": 5677,
        "margin_pct": 59.7768,
        "winner": "REP"
      },
      "23": {
        "dem_votes": 1396,
        "rep_votes": 5138,
        "other_votes": 413,
        "total_votes": 6947,
        "dem_candidate": "Gordon Ball",
        "rep_candidate": "Lamar Alexander",
        "margin": 3742,
        "margin_pct": 53.865,
        "winner": "REP"
      },
      "24": {
        "dem_votes": 1853,
        "rep_votes": 9285,
        "other_votes": 590,
        "total_votes": 11728,
        "dem_candidate": "Gordon Ball",
        "rep_candidate": "Lamar Alexander",
        "margin": 7432,
        "margin_pct": 63.3697,
        "winner": "REP"
      },
      "25": {
        "dem_votes": 4291,
        "rep_votes": 12384,
        "other_votes": 1354,
        "total_votes": 18029,
        "dem_candidate": "Gordon Ball",
        "rep_candidate": "Lamar Alexander",
        "margin": 8093,
        "margin_pct": 44.8888,
        "winner": "REP"
      },
      "31": {
        "dem_votes": 2301,
        "rep_votes": 7875,
        "other_votes": 634,
        "total_votes": 10810,
        "dem_candidate": "Gordon Ball",
        "rep_candidate": "Lamar Alexander",
        "margin": 5574,
        "margin_pct": 51.5634,
        "winner": "REP"
      },
      "32": {
        "dem_votes": 3250,
        "rep_votes": 9228,
        "other_votes": 812,
        "total_votes": 13290,
        "dem_candidate": "Gordon Ball",
        "rep_candidate": "Lamar Alexander",
        "margin": 5978,
        "margin_pct": 44.9812,
        "winner": "REP"
      },
      "33": {
        "dem_votes": 3795,
        "rep_votes": 8848,
        "other_votes": 863,
        "total_votes": 13506,
        "dem_candidate": "Gordon Ball",
        "rep_candidate": "Lamar Alexander",
        "margin": 5053,
        "margin_pct": 37.413,
        "winner": "REP"
      },
      "34": {
        "dem_votes": 3694,
        "rep_votes": 6345,
        "other_votes": 858,
        "total_votes": 10897,
        "dem_candidate": "Gordon Ball",
        "rep_candidate": "Lamar Alexander",
        "margin": 2651,
        "margin_pct": 24.3278,
        "winner": "REP"
      },
      "35": {
        "dem_votes": 2606,
        "rep_votes": 7395,
        "other_votes": 639,
        "total_votes": 10640,
        "dem_candidate": "Gordon Ball",
        "rep_candidate": "Lamar Alexander",
        "margin": 4789,
        "margin_pct": 45.0094,
        "winner": "REP"
      },
      "36": {
        "dem_votes": 2534,
        "rep_votes": 6585,
        "other_votes": 522,
        "total_votes": 9641,
        "dem_candidate": "Gordon Ball",
        "rep_candidate": "Lamar Alexander",
        "margin": 4051,
        "margin_pct": 42.0185,
        "winner": "REP"
      },
      "37": {
        "dem_votes": 3274,
        "rep_votes": 5950,
        "other_votes": 757,
        "total_votes": 9981,
        "dem_candidate": "Gordon Ball",
        "rep_candidate": "Lamar Alexander",
        "margin": 2676,
        "margin_pct": 26.8109,
        "winner": "REP"
      },
      "38": {
        "dem_votes": 2455,
        "rep_votes": 6568,
        "other_votes": 643,
        "total_votes": 9666,
        "dem_candidate": "Gordon Ball",
        "rep_candidate": "Lamar Alexander",
        "margin": 4113,
        "margin_pct": 42.5512,
        "winner": "REP"
      },
      "39": {
        "dem_votes": 4276,
        "rep_votes": 8470,
        "other_votes": 804,
        "total_votes": 13550,
        "dem_candidate": "Gordon Ball",
        "rep_candidate": "Lamar Alexander",
        "margin": 4194,
        "margin_pct": 30.952,
        "winner": "REP"
      },
      "40": {
        "dem_votes": 3119,
        "rep_votes": 5672,
        "other_votes": 680,
        "total_votes": 9471,
        "dem_candidate": "Gordon Ball",
        "rep_candidate": "Lamar Alexander",
        "margin": 2553,
        "margin_pct": 26.956,
        "winner": "REP"
      },
      "41": {
        "dem_votes": 3194,
        "rep_votes": 6588,
        "other_votes": 891,
        "total_votes": 10673,
        "dem_candidate": "Gordon Ball",
        "rep_candidate": "Lamar Alexander",
        "margin": 3394,
        "margin_pct": 31.7999,
        "winner": "REP"
      },
      "42": {
        "dem_votes": 2278,
        "rep_votes": 5527,
        "other_votes": 1074,
        "total_votes": 8879,
        "dem_candidate": "Gordon Ball",
        "rep_candidate": "Lamar Alexander",
        "margin": 3249,
        "margin_pct": 36.592,
        "winner": "REP"
      },
      "43": {
        "dem_votes": 2745,
        "rep_votes": 5682,
        "other_votes": 781,
        "total_votes": 9208,
        "dem_candidate": "Gordon Ball",
        "rep_candidate": "Lamar Alexander",
        "margin": 2937,
        "margin_pct": 31.8962,
        "winner": "REP"
      },
      "44": {
        "dem_votes": 153,
        "rep_votes": 477,
        "other_votes": 64,
        "total_votes": 694,
        "dem_candidate": "Gordon Ball",
        "rep_candidate": "Lamar Alexander",
        "margin": 324,
        "margin_pct": 46.6859,
        "winner": "REP"
      },
      "46": {
        "dem_votes": 3956,
        "rep_votes": 9570,
        "other_votes": 1027,
        "total_votes": 14553,
        "dem_candidate": "Gordon Ball",
        "rep_candidate": "Lamar Alexander",
        "margin": 5614,
        "margin_pct": 38.5762,
        "winner": "REP"
      },
      "47": {
        "dem_votes": 679,
        "rep_votes": 1489,
        "other_votes": 164,
        "total_votes": 2332,
        "dem_candidate": "Gordon Ball",
        "rep_candidate": "Lamar Alexander",
        "margin": 810,
        "margin_pct": 34.7341,
        "winner": "REP"
      },
      "48": {
        "dem_votes": 2393,
        "rep_votes": 5393,
        "other_votes": 703,
        "total_votes": 8489,
        "dem_candidate": "Gordon Ball",
        "rep_candidate": "Lamar Alexander",
        "margin": 3000,
        "margin_pct": 35.3399,
        "winner": "REP"
      },
      "49": {
        "dem_votes": 3735,
        "rep_votes": 7947,
        "other_votes": 880,
        "total_votes": 12562,
        "dem_candidate": "Gordon Ball",
        "rep_candidate": "Lamar Alexander",
        "margin": 4212,
        "margin_pct": 33.5297,
        "winner": "REP"
      },
      "50": {
        "dem_votes": 6340,
        "rep_votes": 3608,
        "other_votes": 589,
        "total_votes": 10537,
        "dem_candidate": "Gordon Ball",
        "rep_candidate": "Lamar Alexander",
        "margin": -2732,
        "margin_pct": -25.9277,
        "winner": "DEM"
      },
      "51": {
        "dem_votes": 6175,
        "rep_votes": 2102,
        "other_votes": 593,
        "total_votes": 8870,
        "dem_candidate": "Gordon Ball",
        "rep_candidate": "Lamar Alexander",
        "margin": -4073,
        "margin_pct": -45.9188,
        "winner": "DEM"
      },
      "52": {
        "dem_votes": 4573,
        "rep_votes": 5051,
        "other_votes": 515,
        "total_votes": 10139,
        "dem_candidate": "Gordon Ball",
        "rep_candidate": "Lamar Alexander",
        "margin": 478,
        "margin_pct": 4.7145,
        "winner": "REP"
      },
      "53": {
        "dem_votes": 4400,
        "rep_votes": 3424,
        "other_votes": 448,
        "total_votes": 8272,
        "dem_candidate": "Gordon Ball",
        "rep_candidate": "Lamar Alexander",
        "margin": -976,
        "margin_pct": -11.7988,
        "winner": "DEM"
      },
      "54": {
        "dem_votes": 5752,
        "rep_votes": 2190,
        "other_votes": 388,
        "total_votes": 8330,
        "dem_candidate": "Gordon Ball",
        "rep_candidate": "Lamar Alexander",
        "margin": -3562,
        "margin_pct": -42.7611,
        "winner": "DEM"
      },
      "55": {
        "dem_votes": 5464,
        "rep_votes": 3690,
        "other_votes": 593,
        "total_votes": 9747,
        "dem_candidate": "Gordon Ball",
        "rep_candidate": "Lamar Alexander",
        "margin": -1774,
        "margin_pct": -18.2005,
        "winner": "DEM"
      },
      "56": {
        "dem_votes": 6498,
        "rep_votes": 6668,
        "other_votes": 704,
        "total_votes": 13870,
        "dem_candidate": "Gordon Ball",
        "rep_candidate": "Lamar Alexander",
        "margin": 170,
        "margin_pct": 1.2257,
        "winner": "REP"
      },
      "57": {
        "dem_votes": 3710,
        "rep_votes": 9801,
        "other_votes": 1099,
        "total_votes": 14610,
        "dem_candidate": "Gordon Ball",
        "rep_candidate": "Lamar Alexander",
        "margin": 6091,
        "margin_pct": 41.6906,
        "winner": "REP"
      },
      "58": {
        "dem_votes": 8652,
        "rep_votes": 6384,
        "other_votes": 891,
        "total_votes": 15927,
        "dem_candidate": "Gordon Ball",
        "rep_candidate": "Lamar Alexander",
        "margin": -2268,
        "margin_pct": -14.24,
        "winner": "DEM"
      },
      "59": {
        "dem_votes": 4391,
        "rep_votes": 5658,
        "other_votes": 523,
        "total_votes": 10572,
        "dem_candidate": "Gordon Ball",
        "rep_candidate": "Lamar Alexander",
        "margin": 1267,
        "margin_pct": 11.9845,
        "winner": "REP"
      },
      "60": {
        "dem_votes": 6752,
        "rep_votes": 7686,
        "other_votes": 954,
        "total_votes": 15392,
        "dem_candidate": "Gordon Ball",
        "rep_candidate": "Lamar Alexander",
        "margin": 934,
        "margin_pct": 6.0681,
        "winner": "REP"
      },
      "61": {
        "dem_votes": 3850,
        "rep_votes": 13606,
        "other_votes": 931,
        "total_votes": 18387,
        "dem_candidate": "Gordon Ball",
        "rep_candidate": "Lamar Alexander",
        "margin": 9756,
        "margin_pct": 53.0592,
        "winner": "REP"
      },
      "62": {
        "dem_votes": 2118,
        "rep_votes": 5808,
        "other_votes": 623,
        "total_votes": 8549,
        "dem_candidate": "Gordon Ball",
        "rep_candidate": "Lamar Alexander",
        "margin": 3690,
        "margin_pct": 43.1629,
        "winner": "REP"
      },
      "63": {
        "dem_votes": 3633,
        "rep_votes": 12437,
        "other_votes": 1114,
        "total_votes": 17184,
        "dem_candidate": "Gordon Ball",
        "rep_candidate": "Lamar Alexander",
        "margin": 8804,
        "margin_pct": 51.2337,
        "winner": "REP"
      },
      "64": {
        "dem_votes": 2213,
        "rep_votes": 5234,
        "other_votes": 555,
        "total_votes": 8002,
        "dem_candidate": "Gordon Ball",
        "rep_candidate": "Lamar Alexander",
        "margin": 3021,
        "margin_pct": 37.7531,
        "winner": "REP"
      },
      "65": {
        "dem_votes": 2164,
        "rep_votes": 7530,
        "other_votes": 810,
        "total_votes": 10504,
        "dem_candidate": "Gordon Ball",
        "rep_candidate": "Lamar Alexander",
        "margin": 5366,
        "margin_pct": 51.0853,
        "winner": "REP"
      },
      "66": {
        "dem_votes": 3448,
        "rep_votes": 8128,
        "other_votes": 1057,
        "total_votes": 12633,
        "dem_candidate": "Gordon Ball",
        "rep_candidate": "Lamar Alexander",
        "margin": 4680,
        "margin_pct": 37.0458,
        "winner": "REP"
      },
      "67": {
        "dem_votes": 2144,
        "rep_votes": 4843,
        "other_votes": 503,
        "total_votes": 7490,
        "dem_candidate": "Gordon Ball",
        "rep_candidate": "Lamar Alexander",
        "margin": 2699,
        "margin_pct": 36.0347,
        "winner": "REP"
      },
      "68": {
        "dem_votes": 2044,
        "rep_votes": 3197,
        "other_votes": 353,
        "total_votes": 5594,
        "dem_candidate": "Gordon Ball",
        "rep_candidate": "Lamar Alexander",
        "margin": 1153,
        "margin_pct": 20.6114,
        "winner": "REP"
      },
      "69": {
        "dem_votes": 3437,
        "rep_votes": 6520,
        "other_votes": 881,
        "total_votes": 10838,
        "dem_candidate": "Gordon Ball",
        "rep_candidate": "Lamar Alexander",
        "margin": 3083,
        "margin_pct": 28.4462,
        "winner": "REP"
      },
      "70": {
        "dem_votes": 2897,
        "rep_votes": 6728,
        "other_votes": 729,
        "total_votes": 10354,
        "dem_candidate": "Gordon Ball",
        "rep_candidate": "Lamar Alexander",
        "margin": 3831,
        "margin_pct": 37.0002,
        "winner": "REP"
      },
      "71": {
        "dem_votes": 2044,
        "rep_votes": 6305,
        "other_votes": 646,
        "total_votes": 8995,
        "dem_candidate": "Gordon Ball",
        "rep_candidate": "Lamar Alexander",
        "margin": 4261,
        "margin_pct": 47.3708,
        "winner": "REP"
      },
      "72": {
        "dem_votes": 1477,
        "rep_votes": 3775,
        "other_votes": 496,
        "total_votes": 5748,
        "dem_candidate": "Gordon Ball",
        "rep_candidate": "Lamar Alexander",
        "margin": 2298,
        "margin_pct": 39.9791,
        "winner": "REP"
      },
      "73": {
        "dem_votes": 967,
        "rep_votes": 2001,
        "other_votes": 271,
        "total_votes": 3239,
        "dem_candidate": "Gordon Ball",
        "rep_candidate": "Lamar Alexander",
        "margin": 1034,
        "margin_pct": 31.9234,
        "winner": "REP"
      },
      "74": {
        "dem_votes": 2210,
        "rep_votes": 3818,
        "other_votes": 495,
        "total_votes": 6523,
        "dem_candidate": "Gordon Ball",
        "rep_candidate": "Lamar Alexander",
        "margin": 1608,
        "margin_pct": 24.6512,
        "winner": "REP"
      },
      "75": {
        "dem_votes": 1749,
        "rep_votes": 3245,
        "other_votes": 369,
        "total_votes": 5363,
        "dem_candidate": "Gordon Ball",
        "rep_candidate": "Lamar Alexander",
        "margin": 1496,
        "margin_pct": 27.8948,
        "winner": "REP"
      },
      "76": {
        "dem_votes": 777,
        "rep_votes": 2012,
        "other_votes": 217,
        "total_votes": 3006,
        "dem_candidate": "Gordon Ball",
        "rep_candidate": "Lamar Alexander",
        "margin": 1235,
        "margin_pct": 41.0845,
        "winner": "REP"
      },
      "77": {
        "dem_votes": 2406,
        "rep_votes": 8133,
        "other_votes": 1161,
        "total_votes": 11700,
        "dem_candidate": "Gordon Ball",
        "rep_candidate": "Lamar Alexander",
        "margin": 5727,
        "margin_pct": 48.9487,
        "winner": "REP"
      },
      "78": {
        "dem_votes": 3104,
        "rep_votes": 7094,
        "other_votes": 887,
        "total_votes": 11085,
        "dem_candidate": "Gordon Ball",
        "rep_candidate": "Lamar Alexander",
        "margin": 3990,
        "margin_pct": 35.9946,
        "winner": "REP"
      },
      "79": {
        "dem_votes": 328,
        "rep_votes": 1489,
        "other_votes": 225,
        "total_votes": 2042,
        "dem_candidate": "Gordon Ball",
        "rep_candidate": "Lamar Alexander",
        "margin": 1161,
        "margin_pct": 56.856,
        "winner": "REP"
      },
      "80": {
        "dem_votes": 3244,
        "rep_votes": 4251,
        "other_votes": 483,
        "total_votes": 7978,
        "dem_candidate": "Gordon Ball",
        "rep_candidate": "Lamar Alexander",
        "margin": 1007,
        "margin_pct": 12.6222,
        "winner": "REP"
      },
      "81": {
        "dem_votes": 2825,
        "rep_votes": 8550,
        "other_votes": 869,
        "total_votes": 12244,
        "dem_candidate": "Gordon Ball",
        "rep_candidate": "Lamar Alexander",
        "margin": 5725,
        "margin_pct": 46.7576,
        "winner": "REP"
      },
      "82": {
        "dem_votes": 2622,
        "rep_votes": 4500,
        "other_votes": 424,
        "total_votes": 7546,
        "dem_candidate": "Gordon Ball",
        "rep_candidate": "Lamar Alexander",
        "margin": 1878,
        "margin_pct": 24.8874,
        "winner": "REP"
      },
      "89": {
        "dem_votes": 3138,
        "rep_votes": 6459,
        "other_votes": 684,
        "total_votes": 10281,
        "dem_candidate": "Gordon Ball",
        "rep_candidate": "Lamar Alexander",
        "margin": 3321,
        "margin_pct": 32.3023,
        "winner": "REP"
      },
      "92": {
        "dem_votes": 2651,
        "rep_votes": 5840,
        "other_votes": 602,
        "total_votes": 9093,
        "dem_candidate": "Gordon Ball",
        "rep_candidate": "Lamar Alexander",
        "margin": 3189,
        "margin_pct": 35.0709,
        "winner": "REP"
      },
      "94": {
        "dem_votes": 3331,
        "rep_votes": 9097,
        "other_votes": 780,
        "total_votes": 13208,
        "dem_candidate": "Gordon Ball",
        "rep_candidate": "Lamar Alexander",
        "margin": 5766,
        "margin_pct": 43.6554,
        "winner": "REP"
      }
    }
  }
}